topsis/__init__.py
topsis/__main__.py
topsis/csvConverter.py
topsis_sidharth_102218069-0.5.dist-info/LICENSE
topsis_sidharth_102218069-0.5.dist-info/METADATA
topsis_sidharth_102218069-0.5.dist-info/WHEEL
topsis_sidharth_102218069-0.5.dist-info/entry_points.txt
topsis_sidharth_102218069-0.5.dist-info/top_level.txt
topsis_sidharth_102218069-0.5.dist-info/RECORD
