Metadata-Version: 2.1
Name: topsis-sidharth-102218069
Version: 0.5
Summary: A Python package to perform TOPSIS analysis.
Home-page: https://github.com/sidharthd7/Topsis-Sidharth-102218069
Author: Sidharth Dhawan
Author-email: sidharthdhawan17@gmail.com
License: MIT
License-File: LICENSE
Requires-Dist: pandas
Requires-Dist: numpy
